capitolscraper/__init__.py
capitolscraper/trades.py
capitolscraper/utils/__init__.py
capitolscraper/utils/scraperfuncs.py
capitolscraper/utils/dataclasses/__init__.py
capitolscraper/utils/dataclasses/page_data.py
capitolscraper/utils/dataclasses/trade.py
capitolscraper/utils/dataclasses/trade_stats.py
capitolscraper/utils/dataclasses/traded_issuer.py
capitolscraper-0.1.dist-info/METADATA
capitolscraper-0.1.dist-info/WHEEL
capitolscraper-0.1.dist-info/RECORD
