Metadata-Version: 2.4
Name: capitolscraper
Version: 0.1
Summary: Web scraper for capitoltrades.com
Requires-Python: >=3.9
Requires-Dist: beautifulsoup4>=4.12.3
Requires-Dist: httpx>=0.28.1
